torchaddition/__init__.py
torchaddition/addition_module.py
torchaddition-0.1.0.dist-info/METADATA
torchaddition-0.1.0.dist-info/WHEEL
torchaddition-0.1.0.dist-info/top_level.txt
torchaddition-0.1.0.dist-info/RECORD
